generation_models/__init__.py
generation_models/generation_models.py
generation_models/py.typed
generation_models/unit_types.py
generation_models/utils/__init__.py
generation_models/utils/df.py
generation_models/utils/psm_readers.py
generation_models/utils/pvsyst_readers.py
generation_models/v0_output_schema.py
generation_models/v2_output_schema.py
generation_models-0.11.3.dist-info/METADATA
generation_models-0.11.3.dist-info/WHEEL
generation_models-0.11.3.dist-info/RECORD
