Metadata-Version: 2.4
Name: generation-models
Version: 0.11.3
Summary: generation API data model
Author: battery_al
Author-email: allenlawrence94@gmail.com
Requires-Python: >=3.10
Classifier: Programming Language :: Python :: 3
Classifier: Programming Language :: Python :: 3.10
Classifier: Programming Language :: Python :: 3.11
Classifier: Programming Language :: Python :: 3.12
Classifier: Programming Language :: Python :: 3.13
Classifier: Programming Language :: Python :: 3.14
Requires-Dist: pandas (>=2.0.0,<3.0.0)
Requires-Dist: pydantic (>=2.11.7,<3.0.0)
